minilvo/__init__.py
minilvo/client.py
minilvo/meta.py
minilvo-0.0.4.dist-info/METADATA
minilvo-0.0.4.dist-info/WHEEL
minilvo-0.0.4.dist-info/top_level.txt
minilvo-0.0.4.dist-info/RECORD
