Metadata-Version: 2.1
Name: minilvo
Version: 0.0.4
Summary: Python API to upload data to ILVO's minio server
Author: Lorenzo Mogicato
Author-email: <lorenzo.mogicato@gmail.com>
License: UNKNOWN
Platform: UNKNOWN
Requires-Dist: minio
Requires-Dist: pillow
Requires-Dist: pydantic
